ezprocess/__init__.py
ezprocess/analysis.py
ezprocess/loader.py
ezprocess/preprocessing.py
ezprocess/tiling.py
ezprocess-0.1.0.dist-info/METADATA
ezprocess-0.1.0.dist-info/WHEEL
ezprocess-0.1.0.dist-info/licenses/LICENSE
ezprocess-0.1.0.dist-info/RECORD
