Metadata-Version: 2.4
Name: ezprocess
Version: 0.1.0
Summary: Preprocess, tile, analyze and geospatial datasets for ML/DL training and evaluation.
Author: Jeffrey Blay, Gazali Agboola
License: MIT
License-File: LICENSE
Keywords: deep-learning,flood,geospatial,machine-learning,raster,remote-sensing
Classifier: Intended Audience :: Science/Research
Classifier: License :: OSI Approved :: MIT License
Classifier: Programming Language :: Python :: 3
Classifier: Programming Language :: Python :: 3.10
Classifier: Programming Language :: Python :: 3.11
Classifier: Topic :: Scientific/Engineering :: Artificial Intelligence
Classifier: Topic :: Scientific/Engineering :: GIS
Requires-Python: >=3.9
Requires-Dist: laspy>=2.5
Requires-Dist: matplotlib>=3.6
Requires-Dist: numpy>=1.23
Requires-Dist: pandas>=1.5
Requires-Dist: rasterio>=1.3
Requires-Dist: scikit-learn>=1.2
Requires-Dist: seaborn>=0.12
Requires-Dist: shap>=0.43
Requires-Dist: statsmodels>=0.14
Requires-Dist: tensorflow>=2.12
Requires-Dist: xgboost>=1.7
